ConversationAgent/LibStage.py
ConversationAgent/README.md
ConversationAgent/__agent__.py
ConversationAgent/__init__.py
ConversationAgent/__memory__.py
ConversationAgent/__nlp_tool__.py
ConversationAgent/__stage__.py
ConversationAgent/__tool__.py
ConversationAgent/jieba_zh/README.md
ConversationAgent/jieba_zh/__init__.py
ConversationAgent/jieba_zh/__main__.py
ConversationAgent/jieba_zh/_compat.py
ConversationAgent/jieba_zh/dict.txt
ConversationAgent/jieba_zh/analyse/__init__.py
ConversationAgent/jieba_zh/analyse/analyzer.py
ConversationAgent/jieba_zh/analyse/idf.txt
ConversationAgent/jieba_zh/analyse/textrank.py
ConversationAgent/jieba_zh/analyse/tfidf.py
ConversationAgent/jieba_zh/finalseg/__init__.py
ConversationAgent/jieba_zh/finalseg/prob_emit.py
ConversationAgent/jieba_zh/finalseg/prob_start.py
ConversationAgent/jieba_zh/finalseg/prob_trans.py
ConversationAgent/jieba_zh/posseg/__init__.py
ConversationAgent/jieba_zh/posseg/char_state_tab.py
ConversationAgent/jieba_zh/posseg/prob_emit.py
ConversationAgent/jieba_zh/posseg/prob_start.py
ConversationAgent/jieba_zh/posseg/prob_trans.py
ConversationAgent/jieba_zh/posseg/viterbi.py
ConversationAgent/types/__init__.py
ConversationAgent/types/memory.py
ConversationAgent/types/stage.py
ConversationAgent/types/static.py
ConversationAgent-0.6.0.dist-info/METADATA
ConversationAgent-0.6.0.dist-info/WHEEL
ConversationAgent-0.6.0.dist-info/top_level.txt
ConversationAgent-0.6.0.dist-info/RECORD
