Metadata-Version: 2.1
Name: ConversationAgent
Version: 0.6.0
Summary: ConversationAgent
Home-page: https://github.com/Chunshan-Theta/ConversationAgent
Author: Theta
